vec2vec/__init__.py
vec2vec/main.py
vec2vec/matrix2vec.py
vec2vec/train_Image_SpectralClustering.py
vec2vec/train_MNIST_TestingMatrix2vec.py
vec2vec/train_MNIST_linux.py
vec2vec/node2vec_master/__init__.py
vec2vec/node2vec_master/node2vec.py
vec2vec-0.0.5.dist-info/LICENSE.md
vec2vec-0.0.5.dist-info/METADATA
vec2vec-0.0.5.dist-info/WHEEL
vec2vec-0.0.5.dist-info/top_level.txt
vec2vec-0.0.5.dist-info/RECORD
