Metadata-Version: 2.1
Name: vec2vec
Version: 0.0.5
Summary: vec2vec project
Home-page: https://github.com/pypa/sampleproject
Author: WangXiang
Author-email: xiangwangcn@163.com
License: UNKNOWN
Platform: UNKNOWN
Classifier: Programming Language :: Python :: 3
Classifier: License :: OSI Approved :: Apache Software License
Classifier: Operating System :: OS Independent
